{ "VPCFE" : false , "Contests" : [ { "CATKEY" : null , "CAT" : null , "C" : "United States Senator" , "K" : "1" , "AggID" : "20" , "regvoters" : 0 , "BCxContest" : 0 , "VF" : 1 , "TP" : 16 , "PR" : 16 , "TV" : 13597 , "BC" : 8370 , "RC" : 0 , "RO" : 0 , "CH" : [ "Michael Bennet","Joe O'Dea","T.J. Cole","Brian Peotter","Frank Atwood" ] , "CHAggId" : [ 1,2,3,4,5 ] , "P" : [ "DEM","REP","UNI","LBR","APV" ] , "PCT" : [ 23.6475856226552,72.3708096333051,0.701924240590585,2.16628343216749,1.11339707128162 ] , "V" : [ 1954,5980,58,179,92 ] , "W" : [ 0,0,0,0,0 ] , "CRC" : [ 0,0,0,0,0 ] , "CRO" : [ 0,0,0,0,0 ] , "IsCumulative" : null , "CumulativeVotes" : null , "CumulativeChoices" : null , "CumulativePercentages" : null , "IsContestNoChoice" : 0 },{ "CATKEY" : null , "CAT" : null , "C" : "Representative to the 118th United States Congress - District 4" , "K" : "2" , "AggID" : "140" , "regvoters" : 0 , "BCxContest" : 0 , "VF" : 1 , "TP" : 16 , "PR" : 16 , "TV" : 13597 , "BC" : 8370 , "RC" : 0 , "RO" : 0 , "CH" : [ "Ike McCorkle","Ken Buck","Ryan McGonigal" ] , "CHAggId" : [ 1,2,3 ] , "P" : [ "DEM","REP","ACN" ] , "PCT" : [ 17.7725990432969,78.6091009444376,3.61830001226542 ] , "V" : [ 1449,6409,295 ] , "W" : [ 0,0,0 ] , "CRC" : [ 0,0,0 ] , "CRO" : [ 0,0,0 ] , "IsCumulative" : null , "CumulativeVotes" : null , "CumulativeChoices" : null , "CumulativePercentages" : null , "IsContestNoChoice" : 0 },{ "CATKEY" : null , "CAT" : null , "C" : "Governor/Lieutenant Governor" , "K" : "3" , "AggID" : "210" , "regvoters" : 0 , "BCxContest" : 0 , "VF" : 1 , "TP" : 16 , "PR" : 16 , "TV" : 13597 , "BC" : 8370 , "RC" : 0 , "RO" : 0 , "CH" : [ "Heidi Ganahl / Danny Moore","Jared Polis / Dianne Primavera","Paul No\u00EBl Fiorino / Cynthia Munhos de Aquino Sirianni","Danielle Neuschwanger / Darryl Gibbs","Kevin Ruskusky / Michele Poague" ] , "CHAggId" : [ 1,2,3,4,5 ] , "P" : [ "REP","DEM","UNI","ACN","LBR" ] , "PCT" : [ 71.765988372093,22.5290697674419,0.254360465116279,4.45736434108527,0.993217054263566 ] , "V" : [ 5925,1860,21,368,82 ] , "W" : [ 0,0,0,0,0 ] , "CRC" : [ 0,0,0,0,0 ] , "CRO" : [ 0,0,0,0,0 ] , "IsCumulative" : null , "CumulativeVotes" : null , "CumulativeChoices" : null , "CumulativePercentages" : null , "IsContestNoChoice" : 0 },{ "CATKEY" : null , "CAT" : null , "C" : "Secretary of State" , "K" : "4" , "AggID" : "220" , "regvoters" : 0 , "BCxContest" : 0 , "VF" : 1 , "TP" : 16 , "PR" : 16 , "TV" : 13597 , "BC" : 8370 , "RC" : 0 , "RO" : 0 , "CH" : [ "Pam Anderson","Jena Griswold","Gary Swing","Jan Kok","Amanda Campbell","Bennett Rutledge" ] , "CHAggId" : [ 1,2,3,4,5,6 ] , "P" : [ "REP","DEM","UNI","APV","ACN","LBR" ] , "PCT" : [ 73.5326285089318,22.7609673107303,0.546846518410499,0.157977883096367,1.40964880301373,1.59193097581723 ] , "V" : [ 6051,1873,45,13,116,131 ] , "W" : [ 0,0,0,0,0,0 ] , "CRC" : [ 0,0,0,0,0,0 ] , "CRO" : [ 0,0,0,0,0,0 ] , "IsCumulative" : null , "CumulativeVotes" : null , "CumulativeChoices" : null , "CumulativePercentages" : null , "IsContestNoChoice" : 0 },{ "CATKEY" : null , "CAT" : null , "C" : "State Treasurer" , "K" : "5" , "AggID" : "230" , "regvoters" : 0 , "BCxContest" : 0 , "VF" : 1 , "TP" : 16 , "PR" : 16 , "TV" : 13597 , "BC" : 8370 , "RC" : 0 , "RO" : 0 , "CH" : [ "Dave Young","Lang Sias","Anthony J. Delgado" ] , "CHAggId" : [ 1,2,3 ] , "P" : [ "DEM","REP","LBR" ] , "PCT" : [ 22.5564848333541,73.6362501560354,3.80726501061041 ] , "V" : [ 1807,5899,305 ] , "W" : [ 0,0,0 ] , "CRC" : [ 0,0,0 ] , "CRO" : [ 0,0,0 ] , "IsCumulative" : null , "CumulativeVotes" : null , "CumulativeChoices" : null , "CumulativePercentages" : null , "IsContestNoChoice" : 0 },{ "CATKEY" : null , "CAT" : null , "C" : "Attorney General" , "K" : "6" , "AggID" : "240" , "regvoters" : 0 , "BCxContest" : 0 , "VF" : 1 , "TP" : 16 , "PR" : 16 , "TV" : 13597 , "BC" : 8370 , "RC" : 0 , "RO" : 0 , "CH" : [ "John Kellner","Phil Weiser","William F. Robinson III" ] , "CHAggId" : [ 1,2,3 ] , "P" : [ "REP","DEM","LBR" ] , "PCT" : [ 75.2491280518186,22.3094170403587,2.44145490782262 ] , "V" : [ 6041,1791,196 ] , "W" : [ 0,0,0 ] , "CRC" : [ 0,0,0 ] , "CRO" : [ 0,0,0 ] , "IsCumulative" : null , "CumulativeVotes" : null , "CumulativeChoices" : null , "CumulativePercentages" : null , "IsContestNoChoice" : 0 },{ "CATKEY" : null , "CAT" : null , "C" : "State Board of Education Member - At Large" , "K" : "7" , "AggID" : "300" , "regvoters" : 0 , "BCxContest" : 0 , "VF" : 1 , "TP" : 16 , "PR" : 16 , "TV" : 13597 , "BC" : 8370 , "RC" : 0 , "RO" : 0 , "CH" : [ "Kathy Plomer","Dan Maloit","Ryan Van Gundy","Eric Bodenstab" ] , "CHAggId" : [ 1,2,3,4 ] , "P" : [ "DEM","REP","LBR","UNI" ] , "PCT" : [ 19.7117208243773,75.9514477177899,3.50233910734606,0.834492350486787 ] , "V" : [ 1559,6007,277,66 ] , "W" : [ 0,0,0,0 ] , "CRC" : [ 0,0,0,0 ] , "CRO" : [ 0,0,0,0 ] , "IsCumulative" : null , "CumulativeVotes" : null , "CumulativeChoices" : null , "CumulativePercentages" : null , "IsContestNoChoice" : 0 },{ "CATKEY" : null , "CAT" : null , "C" : "Regent of the University of Colorado - Congressional District 4" , "K" : "8" , "AggID" : "440" , "regvoters" : 0 , "BCxContest" : 0 , "VF" : 1 , "TP" : 16 , "PR" : 16 , "TV" : 13597 , "BC" : 8370 , "RC" : 0 , "RO" : 0 , "CH" : [ "Jack Barrington","Frank McNulty" ] , "CHAggId" : [ 1,2 ] , "P" : [ "DEM","REP" ] , "PCT" : [ 19.8948178553104,80.1051821446896 ] , "V" : [ 1551,6245 ] , "W" : [ 0,0 ] , "CRC" : [ 0,0 ] , "CRO" : [ 0,0 ] , "IsCumulative" : null , "CumulativeVotes" : null , "CumulativeChoices" : null , "CumulativePercentages" : null , "IsContestNoChoice" : 0 },{ "CATKEY" : null , "CAT" : null , "C" : "State Senator - District 1" , "K" : "9" , "AggID" : "1010" , "regvoters" : 0 , "BCxContest" : 0 , "VF" : 1 , "TP" : 16 , "PR" : 16 , "TV" : 13597 , "BC" : 8370 , "RC" : 0 , "RO" : 0 , "CH" : [ "Byron Pelton" ] , "CHAggId" : [ 1 ] , "P" : [ "REP" ] , "PCT" : [ 100 ] , "V" : [ 6452 ] , "W" : [ 0 ] , "CRC" : [ 0 ] , "CRO" : [ 0 ] , "IsCumulative" : null , "CumulativeVotes" : null , "CumulativeChoices" : null , "CumulativePercentages" : null , "IsContestNoChoice" : 0 },{ "CATKEY" : null , "CAT" : null , "C" : "State Representative - District 63" , "K" : "10" , "AggID" : "2630" , "regvoters" : 0 , "BCxContest" : 0 , "VF" : 1 , "TP" : 16 , "PR" : 16 , "TV" : 13597 , "BC" : 8370 , "RC" : 0 , "RO" : 0 , "CH" : [ "Richard Holtorf" ] , "CHAggId" : [ 1 ] , "P" : [ "REP" ] , "PCT" : [ 100 ] , "V" : [ 6734 ] , "W" : [ 0 ] , "CRC" : [ 0 ] , "CRO" : [ 0 ] , "IsCumulative" : null , "CumulativeVotes" : null , "CumulativeChoices" : null , "CumulativePercentages" : null , "IsContestNoChoice" : 0 },{ "CATKEY" : null , "CAT" : null , "C" : "Logan County Commissioner - District 3" , "K" : "11" , "AggID" : "-1" , "regvoters" : 0 , "BCxContest" : 0 , "VF" : 1 , "TP" : 16 , "PR" : 16 , "TV" : 13597 , "BC" : 8370 , "RC" : 0 , "RO" : 0 , "CH" : [ "Jerry Sonnenberg" ] , "CHAggId" : [ 1 ] , "P" : [ "REP" ] , "PCT" : [ 100 ] , "V" : [ 6940 ] , "W" : [ 0 ] , "CRC" : [ 0 ] , "CRO" : [ 0 ] , "IsCumulative" : null , "CumulativeVotes" : null , "CumulativeChoices" : null , "CumulativePercentages" : null , "IsContestNoChoice" : 0 },{ "CATKEY" : null , "CAT" : null , "C" : "Logan County Clerk and Recorder" , "K" : "12" , "AggID" : "-1" , "regvoters" : 0 , "BCxContest" : 0 , "VF" : 1 , "TP" : 16 , "PR" : 16 , "TV" : 13597 , "BC" : 8370 , "RC" : 0 , "RO" : 0 , "CH" : [ "Pamela M. Bacon" ] , "CHAggId" : [ 1 ] , "P" : [ "REP" ] , "PCT" : [ 100 ] , "V" : [ 7212 ] , "W" : [ 0 ] , "CRC" : [ 0 ] , "CRO" : [ 0 ] , "IsCumulative" : null , "CumulativeVotes" : null , "CumulativeChoices" : null , "CumulativePercentages" : null , "IsContestNoChoice" : 0 },{ "CATKEY" : null , "CAT" : null , "C" : "Logan County Treasurer" , "K" : "13" , "AggID" : "-1" , "regvoters" : 0 , "BCxContest" : 0 , "VF" : 1 , "TP" : 16 , "PR" : 16 , "TV" : 13597 , "BC" : 8370 , "RC" : 0 , "RO" : 0 , "CH" : [ "Patricia Bartlett" ] , "CHAggId" : [ 1 ] , "P" : [ "REP" ] , "PCT" : [ 100 ] , "V" : [ 7114 ] , "W" : [ 0 ] , "CRC" : [ 0 ] , "CRO" : [ 0 ] , "IsCumulative" : null , "CumulativeVotes" : null , "CumulativeChoices" : null , "CumulativePercentages" : null , "IsContestNoChoice" : 0 },{ "CATKEY" : null , "CAT" : null , "C" : "Logan County Assessor" , "K" : "14" , "AggID" : "-1" , "regvoters" : 0 , "BCxContest" : 0 , "VF" : 1 , "TP" : 16 , "PR" : 16 , "TV" : 13597 , "BC" : 8370 , "RC" : 0 , "RO" : 0 , "CH" : [ "Peggy Michaels" ] , "CHAggId" : [ 1 ] , "P" : [ "REP" ] , "PCT" : [ 100 ] , "V" : [ 7037 ] , "W" : [ 0 ] , "CRC" : [ 0 ] , "CRO" : [ 0 ] , "IsCumulative" : null , "CumulativeVotes" : null , "CumulativeChoices" : null , "CumulativePercentages" : null , "IsContestNoChoice" : 0 },{ "CATKEY" : null , "CAT" : null , "C" : "Logan County Sheriff" , "K" : "15" , "AggID" : "-1" , "regvoters" : 0 , "BCxContest" : 0 , "VF" : 1 , "TP" : 16 , "PR" : 16 , "TV" : 13597 , "BC" : 8370 , "RC" : 0 , "RO" : 0 , "CH" : [ "Brett Lane Powell","Craig Gilliland" ] , "CHAggId" : [ 1,2 ] , "P" : [ "REP","UAF" ] , "PCT" : [ 54.3006081668115,45.6993918331885 ] , "V" : [ 4375,3682 ] , "W" : [ 0,0 ] , "CRC" : [ 0,0 ] , "CRO" : [ 0,0 ] , "IsCumulative" : null , "CumulativeVotes" : null , "CumulativeChoices" : null , "CumulativePercentages" : null , "IsContestNoChoice" : 0 },{ "CATKEY" : null , "CAT" : null , "C" : "Logan County Coroner" , "K" : "17" , "AggID" : "-1" , "regvoters" : 0 , "BCxContest" : 0 , "VF" : 1 , "TP" : 16 , "PR" : 16 , "TV" : 13597 , "BC" : 8370 , "RC" : 0 , "RO" : 0 , "CH" : [ "David W. Tennant" ] , "CHAggId" : [ 1 ] , "P" : [ "REP" ] , "PCT" : [ 100 ] , "V" : [ 7058 ] , "W" : [ 0 ] , "CRC" : [ 0 ] , "CRO" : [ 0 ] , "IsCumulative" : null , "CumulativeVotes" : null , "CumulativeChoices" : null , "CumulativePercentages" : null , "IsContestNoChoice" : 0 },{ "CATKEY" : null , "CAT" : null , "C" : "Colorado Court of Appeals Judge - Brown" , "K" : "18" , "AggID" : "3700" , "regvoters" : 0 , "BCxContest" : 0 , "VF" : 1 , "TP" : 16 , "PR" : 16 , "TV" : 13597 , "BC" : 8370 , "RC" : 0 , "RO" : 0 , "CH" : [ "Yes","No" ] , "CHAggId" : [ 1,2 ] , "P" : [ "Y","N" ] , "PCT" : [ 52.002399880006,47.997600119994 ] , "V" : [ 3467,3200 ] , "W" : [ 0,0 ] , "CRC" : [ 0,0 ] , "CRO" : [ 0,0 ] , "IsCumulative" : null , "CumulativeVotes" : null , "CumulativeChoices" : null , "CumulativePercentages" : null , "IsContestNoChoice" : 0 },{ "CATKEY" : null , "CAT" : null , "C" : "Colorado Court of Appeals Judge - Fox" , "K" : "19" , "AggID" : "3701" , "regvoters" : 0 , "BCxContest" : 0 , "VF" : 1 , "TP" : 16 , "PR" : 16 , "TV" : 13597 , "BC" : 8370 , "RC" : 0 , "RO" : 0 , "CH" : [ "Yes","No" ] , "CHAggId" : [ 1,2 ] , "P" : [ "Y","N" ] , "PCT" : [ 54.0157004830918,45.9842995169082 ] , "V" : [ 3578,3046 ] , "W" : [ 0,0 ] , "CRC" : [ 0,0 ] , "CRO" : [ 0,0 ] , "IsCumulative" : null , "CumulativeVotes" : null , "CumulativeChoices" : null , "CumulativePercentages" : null , "IsContestNoChoice" : 0 },{ "CATKEY" : null , "CAT" : null , "C" : "Colorado Court of Appeals Judge - Gomez" , "K" : "20" , "AggID" : "3702" , "regvoters" : 0 , "BCxContest" : 0 , "VF" : 1 , "TP" : 16 , "PR" : 16 , "TV" : 13597 , "BC" : 8370 , "RC" : 0 , "RO" : 0 , "CH" : [ "Yes","No" ] , "CHAggId" : [ 1,2 ] , "P" : [ "Y","N" ] , "PCT" : [ 51.2231954092419,48.7768045907581 ] , "V" : [ 3392,3230 ] , "W" : [ 0,0 ] , "CRC" : [ 0,0 ] , "CRO" : [ 0,0 ] , "IsCumulative" : null , "CumulativeVotes" : null , "CumulativeChoices" : null , "CumulativePercentages" : null , "IsContestNoChoice" : 0 },{ "CATKEY" : null , "CAT" : null , "C" : "Colorado Court of Appeals Judge - Grove" , "K" : "21" , "AggID" : "3703" , "regvoters" : 0 , "BCxContest" : 0 , "VF" : 1 , "TP" : 16 , "PR" : 16 , "TV" : 13597 , "BC" : 8370 , "RC" : 0 , "RO" : 0 , "CH" : [ "Yes","No" ] , "CHAggId" : [ 1,2 ] , "P" : [ "Y","N" ] , "PCT" : [ 53.6109008327025,46.3890991672975 ] , "V" : [ 3541,3064 ] , "W" : [ 0,0 ] , "CRC" : [ 0,0 ] , "CRO" : [ 0,0 ] , "IsCumulative" : null , "CumulativeVotes" : null , "CumulativeChoices" : null , "CumulativePercentages" : null , "IsContestNoChoice" : 0 },{ "CATKEY" : null , "CAT" : null , "C" : "Colorado Court of Appeals Judge - Johnson" , "K" : "22" , "AggID" : "3704" , "regvoters" : 0 , "BCxContest" : 0 , "VF" : 1 , "TP" : 16 , "PR" : 16 , "TV" : 13597 , "BC" : 8370 , "RC" : 0 , "RO" : 0 , "CH" : [ "Yes","No" ] , "CHAggId" : [ 1,2 ] , "P" : [ "Y","N" ] , "PCT" : [ 52.2035438437074,47.7964561562926 ] , "V" : [ 3447,3156 ] , "W" : [ 0,0 ] , "CRC" : [ 0,0 ] , "CRO" : [ 0,0 ] , "IsCumulative" : null , "CumulativeVotes" : null , "CumulativeChoices" : null , "CumulativePercentages" : null , "IsContestNoChoice" : 0 },{ "CATKEY" : null , "CAT" : null , "C" : "Colorado Court of Appeals Judge - Orlov" , "K" : "23" , "AggID" : "3705" , "regvoters" : 0 , "BCxContest" : 0 , "VF" : 1 , "TP" : 16 , "PR" : 16 , "TV" : 13597 , "BC" : 8370 , "RC" : 0 , "RO" : 0 , "CH" : [ "Yes","No" ] , "CHAggId" : [ 1,2 ] , "P" : [ "Y","N" ] , "PCT" : [ 51.0290556900726,48.9709443099274 ] , "V" : [ 3372,3236 ] , "W" : [ 0,0 ] , "CRC" : [ 0,0 ] , "CRO" : [ 0,0 ] , "IsCumulative" : null , "CumulativeVotes" : null , "CumulativeChoices" : null , "CumulativePercentages" : null , "IsContestNoChoice" : 0 },{ "CATKEY" : null , "CAT" : null , "C" : "Colorado Court of Appeals Judge - Pawar" , "K" : "24" , "AggID" : "3706" , "regvoters" : 0 , "BCxContest" : 0 , "VF" : 1 , "TP" : 16 , "PR" : 16 , "TV" : 13597 , "BC" : 8370 , "RC" : 0 , "RO" : 0 , "CH" : [ "Yes","No" ] , "CHAggId" : [ 1,2 ] , "P" : [ "Y","N" ] , "PCT" : [ 50.2573418104753,49.7426581895247 ] , "V" : [ 3320,3286 ] , "W" : [ 0,0 ] , "CRC" : [ 0,0 ] , "CRO" : [ 0,0 ] , "IsCumulative" : null , "CumulativeVotes" : null , "CumulativeChoices" : null , "CumulativePercentages" : null , "IsContestNoChoice" : 0 },{ "CATKEY" : null , "CAT" : null , "C" : "Colorado Court of Appeals Judge - Yun" , "K" : "25" , "AggID" : "3707" , "regvoters" : 0 , "BCxContest" : 0 , "VF" : 1 , "TP" : 16 , "PR" : 16 , "TV" : 13597 , "BC" : 8370 , "RC" : 0 , "RO" : 0 , "CH" : [ "Yes","No" ] , "CHAggId" : [ 1,2 ] , "P" : [ "Y","N" ] , "PCT" : [ 51.0130027214999,48.9869972785001 ] , "V" : [ 3374,3240 ] , "W" : [ 0,0 ] , "CRC" : [ 0,0 ] , "CRO" : [ 0,0 ] , "IsCumulative" : null , "CumulativeVotes" : null , "CumulativeChoices" : null , "CumulativePercentages" : null , "IsContestNoChoice" : 0 },{ "CATKEY" : null , "CAT" : null , "C" : "District Court Judge - 13th Judicial District - Gagliano" , "K" : "26" , "AggID" : "3751" , "regvoters" : 0 , "BCxContest" : 0 , "VF" : 1 , "TP" : 16 , "PR" : 16 , "TV" : 13597 , "BC" : 8370 , "RC" : 0 , "RO" : 0 , "CH" : [ "Yes","No" ] , "CHAggId" : [ 1,2 ] , "P" : [ "Y","N" ] , "PCT" : [ 51.0248901903367,48.9751098096633 ] , "V" : [ 3485,3345 ] , "W" : [ 0,0 ] , "CRC" : [ 0,0 ] , "CRO" : [ 0,0 ] , "IsCumulative" : null , "CumulativeVotes" : null , "CumulativeChoices" : null , "CumulativePercentages" : null , "IsContestNoChoice" : 0 },{ "CATKEY" : null , "CAT" : null , "C" : "Amendment D (CONSTITUTIONAL)" , "K" : "27" , "AggID" : "3900" , "regvoters" : 0 , "BCxContest" : 0 , "VF" : 1 , "TP" : 16 , "PR" : 16 , "TV" : 13597 , "BC" : 8370 , "RC" : 0 , "RO" : 0 , "CH" : [ "Yes/For","No/Against" ] , "CHAggId" : [ 1,2 ] , "P" : [ "Y","N" ] , "PCT" : [ 52.2254411377403,47.7745588622597 ] , "V" : [ 3966,3628 ] , "W" : [ 0,0 ] , "CRC" : [ 0,0 ] , "CRO" : [ 0,0 ] , "IsCumulative" : null , "CumulativeVotes" : null , "CumulativeChoices" : null , "CumulativePercentages" : null , "IsContestNoChoice" : 0 },{ "CATKEY" : null , "CAT" : null , "C" : "Amendment E (CONSTITUTIONAL)" , "K" : "28" , "AggID" : "3901" , "regvoters" : 0 , "BCxContest" : 0 , "VF" : 1 , "TP" : 16 , "PR" : 16 , "TV" : 13597 , "BC" : 8370 , "RC" : 0 , "RO" : 0 , "CH" : [ "Yes/For","No/Against" ] , "CHAggId" : [ 1,2 ] , "P" : [ "Y","N" ] , "PCT" : [ 85.4078323771514,14.5921676228486 ] , "V" : [ 6848,1170 ] , "W" : [ 0,0 ] , "CRC" : [ 0,0 ] , "CRO" : [ 0,0 ] , "IsCumulative" : null , "CumulativeVotes" : null , "CumulativeChoices" : null , "CumulativePercentages" : null , "IsContestNoChoice" : 0 },{ "CATKEY" : null , "CAT" : null , "C" : "Amendment F (CONSTITUTIONAL)" , "K" : "29" , "AggID" : "3902" , "regvoters" : 0 , "BCxContest" : 0 , "VF" : 1 , "TP" : 16 , "PR" : 16 , "TV" : 13597 , "BC" : 8370 , "RC" : 0 , "RO" : 0 , "CH" : [ "Yes/For","No/Against" ] , "CHAggId" : [ 1,2 ] , "P" : [ "Y","N" ] , "PCT" : [ 35.6772184743124,64.3227815256876 ] , "V" : [ 2750,4958 ] , "W" : [ 0,0 ] , "CRC" : [ 0,0 ] , "CRO" : [ 0,0 ] , "IsCumulative" : null , "CumulativeVotes" : null , "CumulativeChoices" : null , "CumulativePercentages" : null , "IsContestNoChoice" : 0 },{ "CATKEY" : null , "CAT" : null , "C" : "Proposition FF (STATUTORY)" , "K" : "30" , "AggID" : "3903" , "regvoters" : 0 , "BCxContest" : 0 , "VF" : 1 , "TP" : 16 , "PR" : 16 , "TV" : 13597 , "BC" : 8370 , "RC" : 0 , "RO" : 0 , "CH" : [ "Yes/For","No/Against" ] , "CHAggId" : [ 1,2 ] , "P" : [ "Y","N" ] , "PCT" : [ 39.5464121948197,60.4535878051803 ] , "V" : [ 3191,4878 ] , "W" : [ 0,0 ] , "CRC" : [ 0,0 ] , "CRO" : [ 0,0 ] , "IsCumulative" : null , "CumulativeVotes" : null , "CumulativeChoices" : null , "CumulativePercentages" : null , "IsContestNoChoice" : 0 },{ "CATKEY" : null , "CAT" : null , "C" : "Proposition GG (STATUTORY)" , "K" : "31" , "AggID" : "3904" , "regvoters" : 0 , "BCxContest" : 0 , "VF" : 1 , "TP" : 16 , "PR" : 16 , "TV" : 13597 , "BC" : 8370 , "RC" : 0 , "RO" : 0 , "CH" : [ "Yes/For","No/Against" ] , "CHAggId" : [ 1,2 ] , "P" : [ "Y","N" ] , "PCT" : [ 59.3637762955362,40.6362237044638 ] , "V" : [ 4628,3168 ] , "W" : [ 0,0 ] , "CRC" : [ 0,0 ] , "CRO" : [ 0,0 ] , "IsCumulative" : null , "CumulativeVotes" : null , "CumulativeChoices" : null , "CumulativePercentages" : null , "IsContestNoChoice" : 0 },{ "CATKEY" : null , "CAT" : null , "C" : "Proposition 121 (STATUTORY)" , "K" : "32" , "AggID" : "3905" , "regvoters" : 0 , "BCxContest" : 0 , "VF" : 1 , "TP" : 16 , "PR" : 16 , "TV" : 13597 , "BC" : 8370 , "RC" : 0 , "RO" : 0 , "CH" : [ "Yes/For","No/Against" ] , "CHAggId" : [ 1,2 ] , "P" : [ "Y","N" ] , "PCT" : [ 76.5204197749399,23.4795802250601 ] , "V" : [ 6052,1857 ] , "W" : [ 0,0 ] , "CRC" : [ 0,0 ] , "CRO" : [ 0,0 ] , "IsCumulative" : null , "CumulativeVotes" : null , "CumulativeChoices" : null , "CumulativePercentages" : null , "IsContestNoChoice" : 0 },{ "CATKEY" : null , "CAT" : null , "C" : "Proposition 122 (STATUTORY)" , "K" : "33" , "AggID" : "3906" , "regvoters" : 0 , "BCxContest" : 0 , "VF" : 1 , "TP" : 16 , "PR" : 16 , "TV" : 13597 , "BC" : 8370 , "RC" : 0 , "RO" : 0 , "CH" : [ "Yes/For","No/Against" ] , "CHAggId" : [ 1,2 ] , "P" : [ "Y","N" ] , "PCT" : [ 32.1320564516129,67.8679435483871 ] , "V" : [ 2550,5386 ] , "W" : [ 0,0 ] , "CRC" : [ 0,0 ] , "CRO" : [ 0,0 ] , "IsCumulative" : null , "CumulativeVotes" : null , "CumulativeChoices" : null , "CumulativePercentages" : null , "IsContestNoChoice" : 0 },{ "CATKEY" : null , "CAT" : null , "C" : "Proposition 123 (STATUTORY)" , "K" : "34" , "AggID" : "3907" , "regvoters" : 0 , "BCxContest" : 0 , "VF" : 1 , "TP" : 16 , "PR" : 16 , "TV" : 13597 , "BC" : 8370 , "RC" : 0 , "RO" : 0 , "CH" : [ "Yes/For","No/Against" ] , "CHAggId" : [ 1,2 ] , "P" : [ "Y","N" ] , "PCT" : [ 29.8292220113852,70.1707779886148 ] , "V" : [ 2358,5547 ] , "W" : [ 0,0 ] , "CRC" : [ 0,0 ] , "CRO" : [ 0,0 ] , "IsCumulative" : null , "CumulativeVotes" : null , "CumulativeChoices" : null , "CumulativePercentages" : null , "IsContestNoChoice" : 0 },{ "CATKEY" : null , "CAT" : null , "C" : "Proposition 124 (STATUTORY)" , "K" : "35" , "AggID" : "3908" , "regvoters" : 0 , "BCxContest" : 0 , "VF" : 1 , "TP" : 16 , "PR" : 16 , "TV" : 13597 , "BC" : 8370 , "RC" : 0 , "RO" : 0 , "CH" : [ "Yes/For","No/Against" ] , "CHAggId" : [ 1,2 ] , "P" : [ "Y","N" ] , "PCT" : [ 35.5348718602576,64.4651281397424 ] , "V" : [ 2787,5056 ] , "W" : [ 0,0 ] , "CRC" : [ 0,0 ] , "CRO" : [ 0,0 ] , "IsCumulative" : null , "CumulativeVotes" : null , "CumulativeChoices" : null , "CumulativePercentages" : null , "IsContestNoChoice" : 0 },{ "CATKEY" : null , "CAT" : null , "C" : "Proposition 125 (STATUTORY)" , "K" : "36" , "AggID" : "3909" , "regvoters" : 0 , "BCxContest" : 0 , "VF" : 1 , "TP" : 16 , "PR" : 16 , "TV" : 13597 , "BC" : 8370 , "RC" : 0 , "RO" : 0 , "CH" : [ "Yes/For","No/Against" ] , "CHAggId" : [ 1,2 ] , "P" : [ "Y","N" ] , "PCT" : [ 42.0889604757775,57.9110395242225 ] , "V" : [ 3397,4674 ] , "W" : [ 0,0 ] , "CRC" : [ 0,0 ] , "CRO" : [ 0,0 ] , "IsCumulative" : null , "CumulativeVotes" : null , "CumulativeChoices" : null , "CumulativePercentages" : null , "IsContestNoChoice" : 0 },{ "CATKEY" : null , "CAT" : null , "C" : "Proposition 126 (STATUTORY)" , "K" : "37" , "AggID" : "3910" , "regvoters" : 0 , "BCxContest" : 0 , "VF" : 1 , "TP" : 16 , "PR" : 16 , "TV" : 13597 , "BC" : 8370 , "RC" : 0 , "RO" : 0 , "CH" : [ "Yes/For","No/Against" ] , "CHAggId" : [ 1,2 ] , "P" : [ "Y","N" ] , "PCT" : [ 39.8094760591627,60.1905239408373 ] , "V" : [ 3176,4802 ] , "W" : [ 0,0 ] , "CRC" : [ 0,0 ] , "CRO" : [ 0,0 ] , "IsCumulative" : null , "CumulativeVotes" : null , "CumulativeChoices" : null , "CumulativePercentages" : null , "IsContestNoChoice" : 0 },{ "CATKEY" : null , "CAT" : null , "C" : "Town of Iliff Referred Ballot Question 2M" , "K" : "40" , "AggID" : "-1" , "regvoters" : 0 , "BCxContest" : 0 , "VF" : 1 , "TP" : 1 , "PR" : 1 , "TV" : 684 , "BC" : 494 , "RC" : 0 , "RO" : 0 , "CH" : [ "Yes/For","No/Against" ] , "CHAggId" : [ 1,2 ] , "P" : [ "Y","N" ] , "PCT" : [ 31.25,68.75 ] , "V" : [ 35,77 ] , "W" : [ 0,0 ] , "CRC" : [ 0,0 ] , "CRO" : [ 0,0 ] , "IsCumulative" : null , "CumulativeVotes" : null , "CumulativeChoices" : null , "CumulativePercentages" : null , "IsContestNoChoice" : 0 },{ "CATKEY" : null , "CAT" : null , "C" : "City of Sterling Referred Ballot Question 2N" , "K" : "38" , "AggID" : "-1" , "regvoters" : 0 , "BCxContest" : 0 , "VF" : 1 , "TP" : 7 , "PR" : 7 , "TV" : 7312 , "BC" : 3832 , "RC" : 0 , "RO" : 0 , "CH" : [ "Yes/For","No/Against" ] , "CHAggId" : [ 1,2 ] , "P" : [ "Y","N" ] , "PCT" : [ 65.729252826027,34.270747173973 ] , "V" : [ 2384,1243 ] , "W" : [ 0,0 ] , "CRC" : [ 0,0 ] , "CRO" : [ 0,0 ] , "IsCumulative" : null , "CumulativeVotes" : null , "CumulativeChoices" : null , "CumulativePercentages" : null , "IsContestNoChoice" : 0 },{ "CATKEY" : null , "CAT" : null , "C" : "Town of Fleming Referred Ballot Question 2P" , "K" : "39" , "AggID" : "-1" , "regvoters" : 0 , "BCxContest" : 0 , "VF" : 1 , "TP" : 1 , "PR" : 1 , "TV" : 539 , "BC" : 360 , "RC" : 0 , "RO" : 0 , "CH" : [ "Yes/For","No/Against" ] , "CHAggId" : [ 1,2 ] , "P" : [ "Y","N" ] , "PCT" : [ 73.1843575418994,26.8156424581006 ] , "V" : [ 131,48 ] , "W" : [ 0,0 ] , "CRC" : [ 0,0 ] , "CRO" : [ 0,0 ] , "IsCumulative" : null , "CumulativeVotes" : null , "CumulativeChoices" : null , "CumulativePercentages" : null , "IsContestNoChoice" : 0 },{ "CATKEY" : null , "CAT" : null , "C" : "Buffalo School District RE-4J Director - District A Recall Question" , "K" : "41" , "AggID" : "5004" , "regvoters" : 0 , "BCxContest" : 0 , "VF" : 1 , "TP" : 2 , "PR" : 2 , "TV" : 1683 , "BC" : 1188 , "RC" : 0 , "RO" : 0 , "CH" : [ "Yes/For","No/Against" ] , "CHAggId" : [ 1,2 ] , "P" : [ "Y","N" ] , "PCT" : [ 54.8179871520343,45.1820128479657 ] , "V" : [ 256,211 ] , "W" : [ 0,0 ] , "CRC" : [ 0,0 ] , "CRO" : [ 0,0 ] , "IsCumulative" : null , "CumulativeVotes" : null , "CumulativeChoices" : null , "CumulativePercentages" : null , "IsContestNoChoice" : 0 },{ "CATKEY" : null , "CAT" : null , "C" : "Buffalo School District RE-4J Director - District A Recall Successor" , "K" : "44" , "AggID" : "5005" , "regvoters" : 0 , "BCxContest" : 0 , "VF" : 1 , "TP" : 2 , "PR" : 2 , "TV" : 1683 , "BC" : 1188 , "RC" : 0 , "RO" : 0 , "CH" : [ "Mike Kirschbaum" ] , "CHAggId" : [ 1 ] , "P" : [ "1" ] , "PCT" : [ 100 ] , "V" : [ 259 ] , "W" : [ 0 ] , "CRC" : [ 0 ] , "CRO" : [ 0 ] , "IsCumulative" : null , "CumulativeVotes" : null , "CumulativeChoices" : null , "CumulativePercentages" : null , "IsContestNoChoice" : 0 },{ "CATKEY" : null , "CAT" : null , "C" : "Plateau RE-5 School District Referred Ballot Issue 4C" , "K" : "42" , "AggID" : "-1" , "regvoters" : 0 , "BCxContest" : 0 , "VF" : 1 , "TP" : 4 , "PR" : 4 , "TV" : 2172 , "BC" : 1546 , "RC" : 0 , "RO" : 0 , "CH" : [ "Yes/For","No/Against" ] , "CHAggId" : [ 1,2 ] , "P" : [ "Y","N" ] , "PCT" : [ 66.8789808917197,33.1210191082803 ] , "V" : [ 210,104 ] , "W" : [ 0,0 ] , "CRC" : [ 0,0 ] , "CRO" : [ 0,0 ] , "IsCumulative" : null , "CumulativeVotes" : null , "CumulativeChoices" : null , "CumulativePercentages" : null , "IsContestNoChoice" : 0 },{ "CATKEY" : null , "CAT" : null , "C" : "Frenchman Groundwater Management District Referred Ballot Issue 7B" , "K" : "45" , "AggID" : "7001" , "regvoters" : 0 , "BCxContest" : 0 , "VF" : 1 , "TP" : 1 , "PR" : 1 , "TV" : 0 , "BC" : 385 , "RC" : 0 , "RO" : 0 , "CH" : [ "Yes/For","No/Against" ] , "CHAggId" : [ 1,2 ] , "P" : [ "Y","N" ] , "PCT" : [ 47.9057591623037,52.0942408376963 ] , "V" : [ 183,199 ] , "W" : [ 0,0 ] , "CRC" : [ 0,0 ] , "CRO" : [ 0,0 ] , "IsCumulative" : null , "CumulativeVotes" : null , "CumulativeChoices" : null , "CumulativePercentages" : null , "IsContestNoChoice" : 0 } ] }